{
  "pools": [
    {
      "rolls": 1,
      "entries": [
        {
          "type": "minecraft:item",
          "name": "casualness_delight:sweet_rice",
          "conditions": [
            {
              "condition": "minecraft:block_state_property",
              "block": "casualness_delight:spring_roll_medley",
              "properties": {
                "servings": "6"
              }
            }
          ]
        }
      ]
    },
    {
      "name": "pool2",
      "rolls": 1,
      "entries": [
        {
          "type": "minecraft:item",
          "name": "minecraft:bowl"
        }
      ],
      "conditions": [
        {
          "condition": "minecraft:inverted",
          "term": {
            "condition": "minecraft:block_state_property",
            "block": "casualness_delight:spring_roll_medley",
            "properties": {
              "servings": "4"
            }
          }
        }
      ]
    }
  ]
}
